Workbook

Sheet Inventory
A1: Link | B1: SKU | C1: Product | D1: Brand | E1: Condition | F1: Cost | G1: Sales Price | H1: Qty | I1: eBay Item ID | J1: Shipping
A2: Dell Latitude 5430 Laptop Computer PC Intel i5 Up To 32GB RAM 1TB SSD Windows 11 | eBay | B2: LAP-DELL-5420-A-001 | C2: Dell Latitude 5420 | D2: Dell | E2: B | F2: =G2*0.775 -> 173.73175 | G2: 224.17 | H2: 10 | I2: 286393092388 | J2: Free
A3: Jumper | B3: LAP-JUMP-5205U-N-001 | C3: 15.6" jumper Windows Laptop | D3: jumper | E3: A | F3: =G3*0.775 -> 131.74225 | G3: 169.99 | H3: 1 | I3: 317575480563 | J3: Free
A4: Microsoft Surface Go Laptop 12.4" i5-1035G1 16GB 256GB SSD Win 11 Pro 1943 PLT | eBay | B4: LAP-MICRO-1943-VG-001 | C4: Microsoft Surface Pro 12.4" Laptop | D4: Microsoft | E4: A | F4: =G4*0.775 -> 185.99225 | G4: 239.99 | H4: 12 | I4: 198143266086 | J4: Free
A5: Acer Aspire 3 15.6" Ryzen 5 7520U 7000 Ser 16GB 1TB SSD Radeon Graphics Refurb | eBay | B5: LAP-ACER-2023-C-001 | C5: Acer Aspire 3 15.6" | D5: Acer | E5: A | F5: =G5*0.775 -> 266.66975 | G5: 344.09 | H5: 12 | I5: 277623301371 | J5: Free
A6: ASUS | B6: LAP-ASUS-69-U-001 | C6: ASUS BR1100CK 11.6" | D6: ASUS | E6: C | F6: =G6*0.775 -> 40.3 | G6: 52 | H6: 10 | I6: 336613650826 | J6: 10
A7: DELL | B7: LAP-DELL-5420-A-002 | C7: Dell Latitude Business Laptop 14" | D7: Dell | E7: C | F7: =G7*0.775 -> 224.47875 | G7: 289.65 | H7: 12 | I7: 286289441911 | J7: Free
A8: Lenovo 300w Gen 3 2-in-1 Touchscreen 11.6" HD Laptop AMD 4GB RAM 64GB SSD Win 11 | eBay | B8: LAP-LEN-69503-A-001 | C8: Lenovo 300w Gen 3 2-in-1 Touchscreen 11.6" | D8: Lenovo | E8: C | F8: =G8*0.775 -> 85.24225 | G8: 109.99 | H8: 12 | I8: 264476753478 | J8: Free
A9: Dell Latitude 15.6” FHD Core i5 Laptop PC Up To 32GB RAM 1TB SSD Windows 11 | eBay | B9: LAP-DELL-5510-A-001 | C9: Dell Latitude 15.6" FHD | D9: Dell | E9: C | F9: =G9*0.775 -> 174.8865 | G9: 225.66 | H9: 1 | I9: 256879744174 | J9: Free
A10: Lenovo ThinkPad L14 Business Laptop 14” FHD Intel i5 16GB RAM 512GB SSD Win 11 | eBay | B10: LAP-LEN-X13 | C10: Lenovo ThinkPad X13 Yoga Gen 2 Laptop 13.3" | D10: Lenovo | E10: C | F10: =G10*0.775 -> 234.577 | G10: 302.68 | H10: 12 | I10: 257114279818 | J10: Free

Sheet Dashboard
A1: 📊 E-COMMERCE INVENTORY DASHBOARD
A3: TOTAL INVENTORY VALUE | E3: TOTAL ESTIMATED PROFIT | I3: TOTAL QUANTITY | M3: ACTIVE LISTINGS
A4: =SUMPRODUCT(Inventory!F2:F100*Inventory!H2:H100) -> 14410.466 | E4: =SUMPRODUCT((Inventory!G2:G100-Inventory!F2:F100)*Inventory!H2:H100) -> 4183.6838 | I4: =SUM(Inventory!H2:H100) -> 82 | M4: =COUNTA(Inventory!B2:B100) -> 9
A5: Cost × Qty | E5: (Price − Cost) × Qty | I5: Units in Stock | M5: SKUs Listed

Sheet _Data
A1: Brand | B1: Inv. Value ($) | C1: Avg Sale Price ($) | D1: Quantity | F1: Condition | G1: Quantity | I1: Product | J1: Price ($)
A2: Acer | B2: =SUMPRODUCT((Inventory!$D$2:$D$100=A2)*(Inventory!$F$2:$F$100)*(Inventory!$H$2:$H$100)) -> 3200.037 | C2: =IFERROR(AVERAGEIF(Inventory!$D$2:$D$100,A2,Inventory!$G$2:$G$100),0) -> 344.09 | D2: =SUMIF(Inventory!$D$2:$D$100,A2,Inventory!$H$2:$H$100) -> 12 | F2: A | G2: =SUMIF(Inventory!$E$2:$E$100,F2,Inventory!$H$2:$H$100) -> 25 | I2: =IFERROR(INDEX(Inventory!$C$2:$C$100,MATCH(LARGE(Inventory!$G$2:$G$100,1),Inventory!$G$2:$G$100,0)),"N/A") -> Acer Aspire 3 15.6" | J2: =IFERROR(LARGE(Inventory!$G$2:$G$100,1),0) -> 344.09
A3: ASUS | B3: =SUMPRODUCT((Inventory!$D$2:$D$100=A3)*(Inventory!$F$2:$F$100)*(Inventory!$H$2:$H$100)) -> 403 | C3: =IFERROR(AVERAGEIF(Inventory!$D$2:$D$100,A3,Inventory!$G$2:$G$100),0) -> 52 | D3: =SUMIF(Inventory!$D$2:$D$100,A3,Inventory!$H$2:$H$100) -> 10 | F3: B | G3: =SUMIF(Inventory!$E$2:$E$100,F3,Inventory!$H$2:$H$100) -> 10 | I3: =IFERROR(INDEX(Inventory!$C$2:$C$100,MATCH(LARGE(Inventory!$G$2:$G$100,2),Inventory!$G$2:$G$100,0)),"N/A") -> Lenovo ThinkPad X13 Yoga Gen 2 Laptop 13.3" | J3: =IFERROR(LARGE(Inventory!$G$2:$G$100,2),0) -> 302.68
A4: Dell | B4: =SUMPRODUCT((Inventory!$D$2:$D$100=A4)*(Inventory!$F$2:$F$100)*(Inventory!$H$2:$H$100)) -> 4605.949 | C4: =IFERROR(AVERAGEIF(Inventory!$D$2:$D$100,A4,Inventory!$G$2:$G$100),0) -> 246.49333 | D4: =SUMIF(Inventory!$D$2:$D$100,A4,Inventory!$H$2:$H$100) -> 23 | F4: C | G4: =SUMIF(Inventory!$E$2:$E$100,F4,Inventory!$H$2:$H$100) -> 47 | I4: =IFERROR(INDEX(Inventory!$C$2:$C$100,MATCH(LARGE(Inventory!$G$2:$G$100,3),Inventory!$G$2:$G$100,0)),"N/A") -> Dell Latitude Business Laptop 14" | J4: =IFERROR(LARGE(Inventory!$G$2:$G$100,3),0) -> 289.65
A5: jumper | B5: =SUMPRODUCT((Inventory!$D$2:$D$100=A5)*(Inventory!$F$2:$F$100)*(Inventory!$H$2:$H$100)) -> 131.74225 | C5: =IFERROR(AVERAGEIF(Inventory!$D$2:$D$100,A5,Inventory!$G$2:$G$100),0) -> 169.99 | D5: =SUMIF(Inventory!$D$2:$D$100,A5,Inventory!$H$2:$H$100) -> 1 | I5: =IFERROR(INDEX(Inventory!$C$2:$C$100,MATCH(LARGE(Inventory!$G$2:$G$100,4),Inventory!$G$2:$G$100,0)),"N/A") -> Microsoft Surface Pro 12.4" Laptop | J5: =IFERROR(LARGE(Inventory!$G$2:$G$100,4),0) -> 239.99
A6: Lenovo | B6: =SUMPRODUCT((Inventory!$D$2:$D$100=A6)*(Inventory!$F$2:$F$100)*(Inventory!$H$2:$H$100)) -> 3837.831 | C6: =IFERROR(AVERAGEIF(Inventory!$D$2:$D$100,A6,Inventory!$G$2:$G$100),0) -> 206.335 | D6: =SUMIF(Inventory!$D$2:$D$100,A6,Inventory!$H$2:$H$100) -> 24 | I6: =IFERROR(INDEX(Inventory!$C$2:$C$100,MATCH(LARGE(Inventory!$G$2:$G$100,5),Inventory!$G$2:$G$100,0)),"N/A") -> Dell Latitude 15.6" FHD | J6: =IFERROR(LARGE(Inventory!$G$2:$G$100,5),0) -> 225.66
A7: Microsoft | B7: =SUMPRODUCT((Inventory!$D$2:$D$100=A7)*(Inventory!$F$2:$F$100)*(Inventory!$H$2:$H$100)) -> 2231.907 | C7: =IFERROR(AVERAGEIF(Inventory!$D$2:$D$100,A7,Inventory!$G$2:$G$100),0) -> 239.99 | D7: =SUMIF(Inventory!$D$2:$D$100,A7,Inventory!$H$2:$H$100) -> 12
